solo/__init__.py
solo/admin.py
solo/apps.py
solo/models.py
solo/py.typed
solo/settings.py
solo/locale/de/LC_MESSAGES/django.mo
solo/locale/de/LC_MESSAGES/django.po
solo/locale/es/LC_MESSAGES/django.mo
solo/locale/es/LC_MESSAGES/django.po
solo/templates/admin/solo/change_form.html
solo/templates/admin/solo/object_history.html
solo/templatetags/__init__.py
solo/templatetags/solo_tags.py
solo/tests/__init__.py
solo/tests/models.py
solo/tests/settings.py
solo/tests/tests.py
solo/tests/testapp2/__init__.py
solo/tests/testapp2/models.py
django_solo-2.4.0.dist-info/LICENSE
django_solo-2.4.0.dist-info/METADATA
django_solo-2.4.0.dist-info/WHEEL
django_solo-2.4.0.dist-info/top_level.txt
django_solo-2.4.0.dist-info/RECORD
