Metadata-Version: 2.1
Name: django-solo
Version: 2.4.0
Summary: Django Solo helps working with singletons
Author: lazybird
Maintainer-email: John Hagen <johnthagen@gmail.com>
License: Creative Commons Attribution 3.0 Unported
Project-URL: Homepage, https://github.com/lazybird/django-solo/
Project-URL: Source, https://github.com/lazybird/django-solo/
Project-URL: Changelog, https://github.com/lazybird/django-solo/blob/master/CHANGES
Classifier: Framework :: Django :: 4.2
Classifier: Framework :: Django :: 5.0
Classifier: Framework :: Django :: 5.1
Classifier: Intended Audience :: Developers
Classifier: Operating System :: OS Independent
Classifier: Programming Language :: Python
Classifier: Programming Language :: Python :: 3
Classifier: Programming Language :: Python :: 3.9
Classifier: Programming Language :: Python :: 3.10
Classifier: Programming Language :: Python :: 3.11
Classifier: Programming Language :: Python :: 3.12
Classifier: Programming Language :: Python :: 3.13
Requires-Python: >=3.9
License-File: LICENSE
Requires-Dist: django>=4.2
Requires-Dist: typing-extensions>=4.0.1; python_version < "3.11"
